{"__type__":"sp.SkeletonData","_name":"monster2b","_native":"raw-skeleton.json","_skeletonJson":{"skeleton":{"hash":"K4weFsi4Cpbmp9189NGIVKX8yxQ","spine":"2.1.27","width":171.01,"height":167.98,"images":""},"bones":[{"name":"root","x":-85.66,"y":0.06},{"name":"bizi","parent":"root","length":64.15,"x":64.19,"y":67.34,"rotation":-177.29},{"name":"body","parent":"root","length":149.34,"x":109.95,"y":25.74,"rotation":89.54},{"name":"eye-01","parent":"root","length":57.41,"x":77.91,"y":64.84,"rotation":90.45},{"name":"eye-02","parent":"root","length":53.46,"x":37.15,"y":78.48,"rotation":89.09},{"name":"eye-05","parent":"root","length":18.13,"x":69.16,"y":84.52,"rotation":88.18},{"name":"eye-06","parent":"root","length":18.44,"x":26.58,"y":94.49,"rotation":92.72},{"name":"eye-07","parent":"root","length":20.54,"x":60.1,"y":95.39,"rotation":88.63},{"name":"eye-08","parent":"root","length":20.89,"x":40.57,"y":97.38,"scaleX":0.864,"scaleY":0.864,"rotation":71.99},{"name":"hand-01","parent":"root","length":48.25,"x":89.98,"y":49.03,"rotation":-90},{"name":"hand-02","parent":"root","length":54.18,"x":132.41,"y":71.5,"rotation":-93.17},{"name":"hand-03","parent":"root","length":47.43,"x":55.45,"y":62.76,"rotation":-89.09},{"name":"lian","parent":"root","length":65.99,"x":78.72,"y":22.47,"rotation":85.01},{"name":"weiba","parent":"root","length":46.02,"x":141.15,"y":107.69,"rotation":49.62}],"slots":[{"name":"hand-03","bone":"hand-03","attachment":"hand-3"},{"name":"weiba","bone":"weiba","attachment":"weiba"},{"name":"body","bone":"body","attachment":"body"},{"name":"eye-02","bone":"eye-02","attachment":"eye-1"},{"name":"eye-08","bone":"eye-08"},{"name":"eye-06","bone":"eye-06"},{"name":"eye-01","bone":"eye-01","attachment":"eye-01"},{"name":"eye-05","bone":"eye-05"},{"name":"eye-07","bone":"eye-07"},{"name":"bizi","bone":"bizi","attachment":"bizi"},{"name":"hand-02","bone":"hand-02","attachment":"hand-02"},{"name":"hand-01","bone":"hand-01","attachment":"hand-2"},{"name":"lian","bone":"lian","attachment":"lian"}],"skins":{"default":{"bizi":{"bizi":{"x":31.74,"y":0.32,"rotation":177.29,"width":65,"height":59}},"body":{"body":{"x":69.58,"y":21.99,"rotation":-89.54,"width":133,"height":145}},"eye-01":{"eye-01":{"x":28.17,"y":3.19,"rotation":-90.45,"width":63,"height":58},"eye-03":{"x":28.17,"y":3.19,"rotation":-90.45,"width":63,"height":58}},"eye-02":{"eye-1":{"path":"eye-01","x":22.46,"y":0.51,"scaleX":0.83,"scaleY":0.83,"rotation":-79.72,"width":63,"height":58},"eye-3":{"path":"eye-03","x":22.46,"y":0.51,"scaleX":0.83,"scaleY":0.83,"rotation":-79.72,"width":63,"height":58}},"eye-05":{"eye-05":{"x":7.12,"y":-4.6,"rotation":-88.18,"width":58,"height":17}},"eye-06":{"eye-5":{"path":"eye-05","x":4.96,"y":-7.02,"scaleX":0.754,"scaleY":0.754,"rotation":-92.72,"width":58,"height":17}},"eye-07":{"eye-07":{"x":6.68,"y":-3.23,"rotation":-88.63,"width":33,"height":18}},"eye-08":{"eye-7":{"path":"eye-07","x":5.79,"y":9.72,"scaleX":-1,"rotation":-85.94,"width":33,"height":18}},"hand-01":{"hand-2":{"path":"hand-02","x":24.53,"y":-0.98,"scaleX":0.996,"scaleY":0.874,"rotation":90,"width":34,"height":56}},"hand-02":{"hand-02":{"x":26.31,"y":4.03,"rotation":93.17,"width":34,"height":56}},"hand-03":{"hand-3":{"path":"hand-02","x":26.4,"y":3.12,"scaleX":0.821,"scaleY":0.821,"rotation":89.09,"width":34,"height":56}},"lian":{"lian":{"x":34.68,"y":-0.25,"rotation":-85.01,"width":62,"height":62}},"weiba":{"weiba":{"x":23.62,"y":1.25,"rotation":-49.62,"width":31,"height":43}}}},"animations":{"dead":{"slots":{"eye-01":{"attachment":[{"time":0,"name":"eye-03"}]},"eye-02":{"attachment":[{"time":0,"name":"eye-3"}]},"eye-05":{"attachment":[{"time":0,"name":null}]},"eye-06":{"attachment":[{"time":0,"name":null}]},"eye-07":{"attachment":[{"time":0,"name":"eye-07"}]},"eye-08":{"attachment":[{"time":0,"name":"eye-7"}]}},"bones":{"eye-07":{"rotate":[{"time":0,"angle":0}],"translate":[{"time":0,"x":0,"y":0}],"scale":[{"time":0,"x":1,"y":1}]},"eye-08":{"rotate":[{"time":0,"angle":0}],"translate":[{"time":0,"x":0,"y":0}],"scale":[{"time":0,"x":1,"y":1}]},"eye-01":{"rotate":[{"time":0,"angle":0}],"translate":[{"time":0,"x":0,"y":0}],"scale":[{"time":0,"x":1,"y":1}]},"eye-02":{"rotate":[{"time":0,"angle":0}],"translate":[{"time":0,"x":0,"y":0}],"scale":[{"time":0,"x":1,"y":1}]},"eye-06":{"rotate":[{"time":0,"angle":0}],"translate":[{"time":0,"x":0,"y":0}],"scale":[{"time":0,"x":1,"y":1}]},"eye-05":{"rotate":[{"time":0,"angle":0}],"translate":[{"time":0,"x":0,"y":0}],"scale":[{"time":0,"x":1,"y":1}]},"weiba":{"rotate":[{"time":0,"angle":0}],"translate":[{"time":0,"x":0,"y":0}],"scale":[{"time":0,"x":1,"y":1}]},"lian":{"rotate":[{"time":0,"angle":0}],"translate":[{"time":0,"x":0,"y":0}],"scale":[{"time":0,"x":1,"y":1}]},"hand-03":{"rotate":[{"time":0,"angle":0}],"translate":[{"time":0,"x":0,"y":0}],"scale":[{"time":0,"x":1,"y":1}]},"hand-02":{"rotate":[{"time":0,"angle":0}],"translate":[{"time":0,"x":0,"y":0}],"scale":[{"time":0,"x":1,"y":1}]},"hand-01":{"rotate":[{"time":0,"angle":0}],"translate":[{"time":0,"x":0,"y":0}],"scale":[{"time":0,"x":1,"y":1}]},"body":{"rotate":[{"time":0,"angle":0}],"translate":[{"time":0,"x":0,"y":0}],"scale":[{"time":0,"x":1,"y":1}]},"bizi":{"rotate":[{"time":0,"angle":0}],"translate":[{"time":0,"x":0,"y":0}],"scale":[{"time":0,"x":1,"y":1}]}}},"hurt":{"slots":{"eye-01":{"attachment":[{"time":0,"name":"eye-03"},{"time":0.4,"name":"eye-03"}]},"eye-02":{"attachment":[{"time":0,"name":"eye-3"},{"time":0.4,"name":"eye-3"}]},"eye-05":{"attachment":[{"time":0,"name":null},{"time":0.4,"name":null}]},"eye-06":{"attachment":[{"time":0,"name":null},{"time":0.4,"name":null}]},"eye-07":{"attachment":[{"time":0,"name":"eye-07"},{"time":0.4,"name":"eye-07"}]},"eye-08":{"attachment":[{"time":0,"name":"eye-7"},{"time":0.4,"name":"eye-7"}]}},"bones":{"eye-01":{"rotate":[{"time":0,"angle":0,"curve":"stepped"},{"time":0.4,"angle":0}],"translate":[{"time":0,"x":0,"y":0},{"time":0.0333,"x":0,"y":-0.32},{"time":0.4,"x":0,"y":0}],"scale":[{"time":0,"x":1,"y":1,"curve":"stepped"},{"time":0.4,"x":1,"y":1}]},"weiba":{"rotate":[{"time":0,"angle":0,"curve":"stepped"},{"time":0.4,"angle":0}],"translate":[{"time":0,"x":0,"y":0},{"time":0.0333,"x":0,"y":-0.32},{"time":0.2,"x":0,"y":-2.95},{"time":0.2333,"x":0,"y":-2.65},{"time":0.4,"x":0,"y":0}],"scale":[{"time":0,"x":1,"y":1,"curve":"stepped"},{"time":0.4,"x":1,"y":1}]},"eye-02":{"rotate":[{"time":0,"angle":0,"curve":"stepped"},{"time":0.4,"angle":0}],"translate":[{"time":0,"x":0,"y":0},{"time":0.0333,"x":0,"y":-0.32},{"time":0.4,"x":0,"y":0}],"scale":[{"time":0,"x":1,"y":1,"curve":"stepped"},{"time":0.4,"x":1,"y":1}]},"eye-05":{"rotate":[{"time":0,"angle":0,"curve":"stepped"},{"time":0.4,"angle":0}],"translate":[{"time":0,"x":0,"y":0},{"time":0.0333,"x":0,"y":-0.32},{"time":0.4,"x":0,"y":0}],"scale":[{"time":0,"x":1,"y":1,"curve":"stepped"},{"time":0.4,"x":1,"y":1}]},"eye-07":{"rotate":[{"time":0,"angle":0,"curve":"stepped"},{"time":0.4,"angle":0}],"translate":[{"time":0,"x":0,"y":0},{"time":0.0333,"x":0,"y":-0.32},{"time":0.4,"x":0,"y":0}],"scale":[{"time":0,"x":1,"y":1,"curve":"stepped"},{"time":0.4,"x":1,"y":1}]},"lian":{"rotate":[{"time":0,"angle":0,"curve":"stepped"},{"time":0.4,"angle":0}],"translate":[{"time":0,"x":0,"y":0},{"time":0.0333,"x":0,"y":-0.32},{"time":0.2,"x":0,"y":-2.95},{"time":0.2333,"x":0,"y":-2.65},{"time":0.4,"x":0,"y":0}],"scale":[{"time":0,"x":1,"y":1,"curve":"stepped"},{"time":0.4,"x":1,"y":1}]},"hand-02":{"rotate":[{"time":0,"angle":0,"curve":"stepped"},{"time":0.4,"angle":0}],"translate":[{"time":0,"x":0,"y":0,"curve":"stepped"},{"time":0.4,"x":0,"y":0}],"scale":[{"time":0,"x":1,"y":1,"curve":"stepped"},{"time":0.4,"x":1,"y":1}]},"bizi":{"rotate":[{"time":0,"angle":0,"curve":"stepped"},{"time":0.4,"angle":0}],"translate":[{"time":0,"x":0,"y":0},{"time":0.0333,"x":0,"y":-0.32},{"time":0.2,"x":0,"y":-2.95},{"time":0.2333,"x":0,"y":-2.65},{"time":0.4,"x":0,"y":0}],"scale":[{"time":0,"x":1,"y":1,"curve":"stepped"},{"time":0.4,"x":1,"y":1}]},"eye-06":{"rotate":[{"time":0,"angle":0,"curve":"stepped"},{"time":0.4,"angle":0}],"translate":[{"time":0,"x":0,"y":0},{"time":0.0333,"x":0,"y":-0.32},{"time":0.4,"x":0,"y":0}],"scale":[{"time":0,"x":1,"y":1,"curve":"stepped"},{"time":0.4,"x":1,"y":1}]},"hand-03":{"rotate":[{"time":0,"angle":0,"curve":"stepped"},{"time":0.4,"angle":0}],"translate":[{"time":0,"x":0,"y":0,"curve":"stepped"},{"time":0.4,"x":0,"y":0}],"scale":[{"time":0,"x":1,"y":1,"curve":"stepped"},{"time":0.4,"x":1,"y":1}]},"eye-08":{"rotate":[{"time":0,"angle":0,"curve":"stepped"},{"time":0.4,"angle":0}],"translate":[{"time":0,"x":0,"y":0},{"time":0.0333,"x":0,"y":-0.32},{"time":0.4,"x":0,"y":0}],"scale":[{"time":0,"x":1,"y":1,"curve":"stepped"},{"time":0.4,"x":1,"y":1}]},"hand-01":{"rotate":[{"time":0,"angle":0,"curve":"stepped"},{"time":0.4,"angle":0}],"translate":[{"time":0,"x":0,"y":0,"curve":"stepped"},{"time":0.4,"x":0,"y":0}],"scale":[{"time":0,"x":1,"y":1,"curve":"stepped"},{"time":0.4,"x":1,"y":1}]},"body":{"rotate":[{"time":0,"angle":0,"curve":"stepped"},{"time":0.4,"angle":0}],"translate":[{"time":0,"x":0,"y":0,"curve":"stepped"},{"time":0.4,"x":0,"y":0}],"scale":[{"time":0,"x":1,"y":1},{"time":0.0333,"x":0.995,"y":1},{"time":0.2,"x":0.953,"y":1.045},{"time":0.2333,"x":0.959,"y":1.045},{"time":0.4,"x":1,"y":1}]},"root":{"rotate":[{"time":0,"angle":0},{"time":0.0333,"angle":-15.84},{"time":0.1666,"angle":2.52},{"time":0.3333,"angle":-0.62,"curve":"stepped"},{"time":0.4,"angle":-0.62}],"translate":[{"time":0,"x":0,"y":0},{"time":0.0333,"x":0,"y":41.34},{"time":0.1666,"x":0,"y":-9.11},{"time":0.3333,"x":0,"y":2.1,"curve":"stepped"},{"time":0.4,"x":0,"y":2.1}],"scale":[{"time":0,"x":1,"y":1,"curve":"stepped"},{"time":0.4,"x":1,"y":1}]}}},"idle":{"slots":{"eye-01":{"attachment":[{"time":0,"name":"eye-01"},{"time":0.9666,"name":"eye-03"},{"time":1,"name":"eye-03"},{"time":1.0333,"name":"eye-03"},{"time":1.0666,"name":"eye-03"},{"time":1.1,"name":"eye-03"},{"time":1.1333,"name":"eye-03"},{"time":1.1666,"name":"eye-01"},{"time":1.4,"name":"eye-01"}]},"eye-02":{"attachment":[{"time":0,"name":"eye-1"},{"time":0.9666,"name":"eye-3"},{"time":1,"name":"eye-3"},{"time":1.0333,"name":"eye-3"},{"time":1.0666,"name":"eye-3"},{"time":1.1,"name":"eye-3"},{"time":1.1333,"name":"eye-3"},{"time":1.1666,"name":"eye-1"},{"time":1.4,"name":"eye-1"}]},"eye-05":{"attachment":[{"time":0,"name":null},{"time":0.9666,"name":"eye-05"},{"time":1,"name":"eye-05"},{"time":1.0333,"name":"eye-05"},{"time":1.0666,"name":"eye-05"},{"time":1.1,"name":"eye-05"},{"time":1.1333,"name":"eye-05"},{"time":1.1666,"name":null},{"time":1.2,"name":null},{"time":1.4,"name":null}]},"eye-06":{"attachment":[{"time":0,"name":null},{"time":0.9666,"name":"eye-5"},{"time":1,"name":"eye-5"},{"time":1.0333,"name":"eye-5"},{"time":1.0666,"name":"eye-5"},{"time":1.1,"name":"eye-5"},{"time":1.1333,"name":"eye-5"},{"time":1.1666,"name":null},{"time":1.2,"name":null},{"time":1.4,"name":null}]},"eye-07":{"attachment":[{"time":0,"name":null},{"time":1.4,"name":null}]},"eye-08":{"attachment":[{"time":0,"name":null},{"time":1.4,"name":null}]}},"bones":{"body":{"rotate":[{"time":0,"angle":0,"curve":"stepped"},{"time":0.4666,"angle":0,"curve":"stepped"},{"time":0.9333,"angle":0,"curve":"stepped"},{"time":1.4,"angle":0}],"translate":[{"time":0,"x":0,"y":0,"curve":"stepped"},{"time":0.4666,"x":0,"y":0,"curve":"stepped"},{"time":0.9333,"x":0,"y":0,"curve":"stepped"},{"time":1.4,"x":0,"y":0}],"scale":[{"time":0,"x":1,"y":1},{"time":0.0333,"x":0.995,"y":1},{"time":0.2333,"x":0.938,"y":1.045},{"time":0.2666,"x":0.959,"y":1.045},{"time":0.4666,"x":1,"y":1},{"time":0.5,"x":0.995,"y":1},{"time":0.7,"x":0.938,"y":1.077},{"time":0.7333,"x":0.959,"y":1.045},{"time":0.9333,"x":1,"y":1},{"time":0.9666,"x":0.995,"y":1},{"time":1.1666,"x":0.938,"y":1.077},{"time":1.2,"x":0.959,"y":1.045},{"time":1.4,"x":1,"y":1}]},"bizi":{"rotate":[{"time":0,"angle":0,"curve":"stepped"},{"time":0.4666,"angle":0,"curve":"stepped"},{"time":0.9333,"angle":0,"curve":"stepped"},{"time":1.4,"angle":0}],"translate":[{"time":0,"x":0,"y":0},{"time":0.0333,"x":0,"y":-0.32},{"time":0.2333,"x":0,"y":-2.95},{"time":0.2666,"x":0,"y":-2.65},{"time":0.4666,"x":0,"y":0},{"time":0.5,"x":0,"y":-0.32},{"time":0.7,"x":0,"y":-2.95},{"time":0.7333,"x":0,"y":-2.65},{"time":0.9333,"x":0,"y":0},{"time":0.9666,"x":0,"y":-0.32},{"time":1.1666,"x":0,"y":-2.95},{"time":1.2,"x":0,"y":-2.65},{"time":1.4,"x":0,"y":0}],"scale":[{"time":0,"x":1,"y":1},{"time":0.2333,"x":1.01,"y":1.095},{"time":0.4666,"x":1,"y":1},{"time":0.7,"x":1.01,"y":1.095,"curve":"stepped"},{"time":0.9333,"x":1.01,"y":1.095},{"time":1.4,"x":1,"y":1}]},"eye-01":{"rotate":[{"time":0,"angle":0,"curve":"stepped"},{"time":0.4666,"angle":0,"curve":"stepped"},{"time":0.9333,"angle":0,"curve":"stepped"},{"time":1.4,"angle":0}],"translate":[{"time":0,"x":0,"y":0},{"time":0.0333,"x":0,"y":-0.32},{"time":0.2333,"x":0,"y":-2.95},{"time":0.2666,"x":0,"y":-2.65},{"time":0.4666,"x":0,"y":0},{"time":0.5,"x":0,"y":-0.32},{"time":0.7,"x":0,"y":-2.95},{"time":0.7333,"x":0,"y":-2.65},{"time":0.9333,"x":0,"y":0},{"time":0.9666,"x":0,"y":-0.32},{"time":1.1666,"x":0,"y":-2.95},{"time":1.2,"x":0,"y":-2.65},{"time":1.4,"x":0,"y":0}],"scale":[{"time":0,"x":1,"y":1,"curve":"stepped"},{"time":0.4666,"x":1,"y":1,"curve":"stepped"},{"time":0.9333,"x":1,"y":1,"curve":"stepped"},{"time":1.4,"x":1,"y":1}]},"eye-02":{"rotate":[{"time":0,"angle":0,"curve":"stepped"},{"time":0.4666,"angle":0,"curve":"stepped"},{"time":0.9333,"angle":0,"curve":"stepped"},{"time":1.4,"angle":0}],"translate":[{"time":0,"x":0,"y":0},{"time":0.0333,"x":0,"y":-0.32},{"time":0.2333,"x":0,"y":-2.95},{"time":0.2666,"x":0,"y":-2.65},{"time":0.4666,"x":0,"y":0},{"time":0.5,"x":0,"y":-0.32},{"time":0.7,"x":0,"y":-2.95},{"time":0.7333,"x":0,"y":-2.65},{"time":0.9333,"x":0,"y":0},{"time":0.9666,"x":0,"y":-0.32},{"time":1.1666,"x":0,"y":-2.95},{"time":1.2,"x":0,"y":-2.65},{"time":1.4,"x":0,"y":0}],"scale":[{"time":0,"x":1,"y":1,"curve":"stepped"},{"time":0.4666,"x":1,"y":1,"curve":"stepped"},{"time":0.9333,"x":1,"y":1,"curve":"stepped"},{"time":1.4,"x":1,"y":1}]},"eye-05":{"rotate":[{"time":0,"angle":0,"curve":"stepped"},{"time":0.4666,"angle":0,"curve":"stepped"},{"time":0.9333,"angle":0,"curve":"stepped"},{"time":1.4,"angle":0}],"translate":[{"time":0,"x":0,"y":0},{"time":0.0333,"x":0,"y":-0.32},{"time":0.2333,"x":0,"y":-2.95},{"time":0.2666,"x":0,"y":-2.65},{"time":0.4666,"x":0,"y":0},{"time":0.5,"x":0,"y":-0.32},{"time":0.7,"x":0,"y":-2.95},{"time":0.7333,"x":0,"y":-2.65},{"time":0.9333,"x":0,"y":0},{"time":0.9666,"x":0,"y":-0.32},{"time":1.1666,"x":0,"y":-2.95},{"time":1.2,"x":0,"y":-2.65},{"time":1.4,"x":0,"y":0}],"scale":[{"time":0,"x":1,"y":1,"curve":"stepped"},{"time":0.4666,"x":1,"y":1,"curve":"stepped"},{"time":0.9333,"x":1,"y":1,"curve":"stepped"},{"time":1.4,"x":1,"y":1}]},"eye-06":{"rotate":[{"time":0,"angle":0,"curve":"stepped"},{"time":0.4666,"angle":0,"curve":"stepped"},{"time":0.9333,"angle":0,"curve":"stepped"},{"time":1.4,"angle":0}],"translate":[{"time":0,"x":0,"y":0},{"time":0.0333,"x":0,"y":-0.32},{"time":0.2333,"x":0,"y":-2.95},{"time":0.4666,"x":0,"y":0},{"time":0.5,"x":0,"y":-0.32},{"time":0.7,"x":0,"y":-2.95},{"time":0.9333,"x":0,"y":0},{"time":0.9666,"x":0,"y":-0.32},{"time":1.1666,"x":0,"y":-2.95},{"time":1.4,"x":0,"y":0}],"scale":[{"time":0,"x":1,"y":1,"curve":"stepped"},{"time":0.4666,"x":1,"y":1,"curve":"stepped"},{"time":0.9333,"x":1,"y":1,"curve":"stepped"},{"time":1.4,"x":1,"y":1}]},"eye-07":{"rotate":[{"time":0,"angle":0,"curve":"stepped"},{"time":0.4666,"angle":0,"curve":"stepped"},{"time":0.9333,"angle":0,"curve":"stepped"},{"time":1.4,"angle":0}],"translate":[{"time":0,"x":0,"y":0},{"time":0.0333,"x":0,"y":-0.32},{"time":0.2333,"x":0,"y":-2.95},{"time":0.2666,"x":0,"y":-2.65},{"time":0.4666,"x":0,"y":0},{"time":0.5,"x":0,"y":-0.32},{"time":0.7,"x":0,"y":-2.95},{"time":0.7333,"x":0,"y":-2.65},{"time":0.9333,"x":0,"y":0},{"time":0.9666,"x":0,"y":-0.32},{"time":1.1666,"x":0,"y":-2.95},{"time":1.2,"x":0,"y":-2.65},{"time":1.4,"x":0,"y":0}],"scale":[{"time":0,"x":1,"y":1,"curve":"stepped"},{"time":0.4666,"x":1,"y":1,"curve":"stepped"},{"time":0.9333,"x":1,"y":1,"curve":"stepped"},{"time":1.4,"x":1,"y":1}]},"eye-08":{"rotate":[{"time":0,"angle":0,"curve":"stepped"},{"time":0.4666,"angle":0,"curve":"stepped"},{"time":0.9333,"angle":0,"curve":"stepped"},{"time":1.4,"angle":0}],"translate":[{"time":0,"x":0,"y":0},{"time":0.0333,"x":0,"y":-0.32},{"time":0.2333,"x":0,"y":-2.95},{"time":0.2666,"x":0,"y":-2.65},{"time":0.4666,"x":0,"y":0},{"time":0.5,"x":0,"y":-0.32},{"time":0.7,"x":0,"y":-2.95},{"time":0.7333,"x":0,"y":-2.65},{"time":0.9333,"x":0,"y":0},{"time":0.9666,"x":0,"y":-0.32},{"time":1.1666,"x":0,"y":-2.95},{"time":1.2,"x":0,"y":-2.65},{"time":1.4,"x":0,"y":0}],"scale":[{"time":0,"x":1,"y":1,"curve":"stepped"},{"time":0.4666,"x":1,"y":1,"curve":"stepped"},{"time":0.9333,"x":1,"y":1,"curve":"stepped"},{"time":1.4,"x":1,"y":1}]},"lian":{"rotate":[{"time":0,"angle":0,"curve":"stepped"},{"time":0.4666,"angle":0,"curve":"stepped"},{"time":0.9333,"angle":0,"curve":"stepped"},{"time":1.4,"angle":0}],"translate":[{"time":0,"x":0,"y":0},{"time":0.0333,"x":0,"y":-0.32},{"time":0.2333,"x":0,"y":-2.95},{"time":0.2666,"x":0,"y":-2.65},{"time":0.4666,"x":0,"y":0},{"time":0.5,"x":0,"y":-0.32},{"time":0.7,"x":0,"y":-2.95},{"time":0.7333,"x":0,"y":-2.65},{"time":0.9333,"x":0,"y":0},{"time":0.9666,"x":0,"y":-0.32},{"time":1.1666,"x":0,"y":-2.95},{"time":1.2,"x":0,"y":-2.65},{"time":1.4,"x":0,"y":0}],"scale":[{"time":0,"x":1,"y":1,"curve":"stepped"},{"time":0.4666,"x":1,"y":1,"curve":"stepped"},{"time":0.9333,"x":1,"y":1,"curve":"stepped"},{"time":1.4,"x":1,"y":1}]},"weiba":{"rotate":[{"time":0,"angle":0},{"time":0.0333,"angle":4.93},{"time":0.2,"angle":-26.01},{"time":0.4,"angle":-54.97},{"time":0.5666,"angle":-73.48},{"time":0.8,"angle":0},{"time":1.0333,"angle":-47.81},{"time":1.4,"angle":0}],"translate":[{"time":0,"x":0,"y":0},{"time":0.0333,"x":0,"y":-0.32},{"time":0.2333,"x":0,"y":-2.95},{"time":0.2666,"x":0,"y":-2.65},{"time":0.4666,"x":0,"y":0},{"time":0.5,"x":0,"y":-0.32},{"time":0.7,"x":0,"y":-2.95},{"time":0.7333,"x":0,"y":-2.65},{"time":0.9333,"x":0,"y":0},{"time":0.9666,"x":0,"y":-0.32},{"time":1.1666,"x":0,"y":-2.95},{"time":1.2,"x":0,"y":-2.65},{"time":1.4,"x":0,"y":0}],"scale":[{"time":0,"x":1,"y":1,"curve":"stepped"},{"time":0.4666,"x":1,"y":1,"curve":"stepped"},{"time":0.9333,"x":1,"y":1,"curve":"stepped"},{"time":1.4,"x":1,"y":1}]},"hand-03":{"rotate":[{"time":0,"angle":0,"curve":"stepped"},{"time":0.4666,"angle":0,"curve":"stepped"},{"time":0.9333,"angle":0,"curve":"stepped"},{"time":1.4,"angle":0}],"translate":[{"time":0,"x":0,"y":0,"curve":"stepped"},{"time":0.4666,"x":0,"y":0,"curve":"stepped"},{"time":0.9333,"x":0,"y":0,"curve":"stepped"},{"time":1.4,"x":0,"y":0}],"scale":[{"time":0,"x":1,"y":1,"curve":"stepped"},{"time":0.4666,"x":1,"y":1,"curve":"stepped"},{"time":0.9333,"x":1,"y":1,"curve":"stepped"},{"time":1.4,"x":1,"y":1}]},"hand-02":{"rotate":[{"time":0,"angle":0,"curve":"stepped"},{"time":0.4666,"angle":0},{"time":0.5333,"angle":9.26},{"time":0.7333,"angle":25.02},{"time":0.8333,"angle":44.91},{"time":1.4,"angle":0}],"translate":[{"time":0,"x":0,"y":0,"curve":"stepped"},{"time":0.4666,"x":0,"y":0,"curve":"stepped"},{"time":0.9333,"x":0,"y":0,"curve":"stepped"},{"time":1.4,"x":0,"y":0}],"scale":[{"time":0,"x":1,"y":1,"curve":"stepped"},{"time":0.4666,"x":1,"y":1,"curve":"stepped"},{"time":0.9333,"x":1,"y":1,"curve":"stepped"},{"time":1.4,"x":1,"y":1}]},"hand-01":{"rotate":[{"time":0,"angle":0},{"time":0.0333,"angle":4.49},{"time":0.3,"angle":16.96},{"time":0.4,"angle":37.68},{"time":0.9333,"angle":0,"curve":"stepped"},{"time":1.4,"angle":0}],"translate":[{"time":0,"x":0,"y":0,"curve":"stepped"},{"time":0.4666,"x":0,"y":0,"curve":"stepped"},{"time":0.9333,"x":0,"y":0,"curve":"stepped"},{"time":1.4,"x":0,"y":0}],"scale":[{"time":0,"x":1,"y":1,"curve":"stepped"},{"time":0.4666,"x":1,"y":1,"curve":"stepped"},{"time":0.9333,"x":1,"y":1,"curve":"stepped"},{"time":1.4,"x":1,"y":1}]}}}}},"_atlasText":"\nmonster2b.png\nsize: 256,256\nformat: RGBA8888\nfilter: Linear,Linear\nrepeat: none\nbizi\n  rotate: false\n  xy: 2, 38\n  size: 65, 59\n  orig: 65, 59\n  offset: 0, 0\n  index: -1\nbody\n  rotate: false\n  xy: 2, 99\n  size: 133, 145\n  orig: 133, 145\n  offset: 0, 0\n  index: -1\neye-01\n  rotate: false\n  xy: 69, 39\n  size: 63, 58\n  orig: 63, 58\n  offset: 0, 0\n  index: -1\neye-03\n  rotate: true\n  xy: 137, 117\n  size: 63, 58\n  orig: 63, 58\n  offset: 0, 0\n  index: -1\neye-05\n  rotate: true\n  xy: 201, 186\n  size: 58, 17\n  orig: 58, 17\n  offset: 0, 0\n  index: -1\neye-07\n  rotate: false\n  xy: 137, 97\n  size: 33, 18\n  orig: 33, 18\n  offset: 0, 0\n  index: -1\nhand-02\n  rotate: true\n  xy: 2, 2\n  size: 34, 56\n  orig: 34, 56\n  offset: 0, 0\n  index: -1\nlian\n  rotate: false\n  xy: 137, 182\n  size: 62, 62\n  orig: 62, 62\n  offset: 0, 0\n  index: -1\nweiba\n  rotate: false\n  xy: 220, 201\n  size: 31, 43\n  orig: 31, 43\n  offset: 0, 0\n  index: -1\n","textures":[{"__uuid__":"26NxY6gnlDir+bv3Q1KoDO"}],"textureNames":["monster2b.png"]}