{"__type__":"sp.SkeletonData","_name":"rabbit","_native":"raw-skeleton.json","_skeletonJson":{"skeleton":{"hash":"vaX/qvcxsav7PNlTkgELnm8Wtn0","spine":"2.1.27","width":73.03,"height":79.02,"images":""},"bones":[{"name":"root","x":-46.36},{"name":"body","parent":"root","length":80.27,"x":45.65,"y":5.21,"rotation":90.9},{"name":"eye01","parent":"root","length":25.28,"x":65.24,"y":36.18,"rotation":90.45},{"name":"eye02","parent":"root","length":25.94,"x":27.95,"y":35.55,"rotation":92.7}],"slots":[{"name":"body","bone":"body","attachment":"body"},{"name":"eye01","bone":"eye01","attachment":"eye01"},{"name":"eye02","bone":"eye02","attachment":"eye1"}],"skins":{"default":{"body":{"body":{"x":40.26,"y":-1.49,"rotation":-90.9,"width":73,"height":79}},"eye01":{"eye01":{"x":9.32,"y":1.16,"rotation":-90.45,"width":10,"height":13},"eye03":{"x":9.32,"y":1.16,"rotation":-90.45,"width":10,"height":13}},"eye02":{"eye1":{"path":"eye01","x":9.93,"y":-0.51,"scaleX":-1,"rotation":-92.7,"width":10,"height":13},"eye3":{"path":"eye03","x":9.93,"y":-0.51,"scaleX":-1,"rotation":-92.7,"width":10,"height":13}}}},"animations":{"idle":{"slots":{"eye01":{"attachment":[{"time":0,"name":"eye01"},{"time":1,"name":"eye03"},{"time":1.1333,"name":"eye03"},{"time":1.1666,"name":"eye01"},{"time":1.4,"name":"eye01"}]},"eye02":{"attachment":[{"time":0,"name":"eye1"},{"time":1,"name":"eye3"},{"time":1.1333,"name":"eye3"},{"time":1.1666,"name":"eye1"},{"time":1.4,"name":"eye1"}]}},"bones":{"eye02":{"rotate":[{"time":0,"angle":0,"curve":"stepped"},{"time":0.4666,"angle":0,"curve":"stepped"},{"time":0.9333,"angle":0,"curve":"stepped"},{"time":1.4,"angle":0}],"translate":[{"time":0,"x":0,"y":0},{"time":0.2333,"x":0,"y":-6.63},{"time":0.4666,"x":0,"y":0},{"time":0.7,"x":0,"y":-6.63},{"time":0.9333,"x":0,"y":0},{"time":1.1666,"x":0,"y":-6.63},{"time":1.4,"x":0,"y":0}],"scale":[{"time":0,"x":1,"y":1,"curve":"stepped"},{"time":0.4666,"x":1,"y":1,"curve":"stepped"},{"time":0.9333,"x":1,"y":1,"curve":"stepped"},{"time":1.4,"x":1,"y":1}]},"eye01":{"rotate":[{"time":0,"angle":0,"curve":"stepped"},{"time":0.4666,"angle":0,"curve":"stepped"},{"time":0.9333,"angle":0,"curve":"stepped"},{"time":1.4,"angle":0}],"translate":[{"time":0,"x":0,"y":0},{"time":0.2333,"x":0,"y":-6.63},{"time":0.4666,"x":0,"y":0},{"time":0.7,"x":0,"y":-6.63},{"time":0.9333,"x":0,"y":0},{"time":1.1666,"x":0,"y":-6.63},{"time":1.4,"x":0,"y":0}],"scale":[{"time":0,"x":1,"y":1,"curve":"stepped"},{"time":0.4666,"x":1,"y":1,"curve":"stepped"},{"time":0.9333,"x":1,"y":1,"curve":"stepped"},{"time":1.4,"x":1,"y":1}]},"body":{"rotate":[{"time":0,"angle":0,"curve":"stepped"},{"time":0.4666,"angle":0,"curve":"stepped"},{"time":0.9333,"angle":0,"curve":"stepped"},{"time":1.4,"angle":0}],"translate":[{"time":0,"x":0,"y":0,"curve":"stepped"},{"time":0.4666,"x":0,"y":0,"curve":"stepped"},{"time":0.9333,"x":0,"y":0,"curve":"stepped"},{"time":1.4,"x":0,"y":0}],"scale":[{"time":0,"x":1,"y":1},{"time":0.2333,"x":0.86,"y":1.057},{"time":0.4666,"x":1,"y":1},{"time":0.7,"x":0.86,"y":1.057},{"time":0.9333,"x":1,"y":1},{"time":1.1666,"x":0.86,"y":1.057},{"time":1.4,"x":1,"y":1}]}}}}},"_atlasText":"\nrabbit.png\nsize: 128,128\nformat: RGBA8888\nfilter: Linear,Linear\nrepeat: none\nbody\n  rotate: false\n  xy: 2, 17\n  size: 73, 79\n  orig: 73, 79\n  offset: 0, 0\n  index: -1\neye01\n  rotate: false\n  xy: 2, 2\n  size: 10, 13\n  orig: 10, 13\n  offset: 0, 0\n  index: -1\neye03\n  rotate: false\n  xy: 77, 83\n  size: 10, 13\n  orig: 10, 13\n  offset: 0, 0\n  index: -1\n","textures":[{"__uuid__":"f2ultirVRGY5O7SQ5cQwsA"}],"textureNames":["rabbit.png"]}